{"prof":[
   {"id":"0","name":"Select Matrimony Profile For"},   
   {"id":"1","name":"Myself"},   
   {"id":"2","name":"Son"},  
   {"id":"3","name":"Daughter"},  
   {"id":"4","name":"Brother"},  
   {"id":"5","name":"Sister"},  
   {"id":"6","name":"Relative"},  
   {"id":"7","name":"Friend"}
],
"religion":[
   {"id":"8","name":"Select Religion"},
   {"id":"9","name":"Hindu"},
   {"id":"10","name":"Muslim - Shia"},
   {"id":"11","name":"Muslim - Sunni"},
   {"id":"12","name":"Muslim - Others"},
   {"id":"13","name":"Christian"},
   {"id":"14","name":"Sikh"},
   {"id":"15","name":"Jain - Digambar"},
   {"id":"16","name":"Jain - Shwetambar"},
   {"id":"17","name":"Jain - Others"},
   {"id":"18","name":"Parsi"},
   {"id":"19","name":"Buddhist"},
   {"id":"20","name":"Inter-Religion"}
],
"mtounge":[
   {"id":"21","name":"Select Mother Tongue"},
   {"id":"22","name":"Assamese"},
   {"id":"23","name":"Bengali"},
   {"id":"24","name":"English"},
   {"id":"25","name":"Gujarati"},
   {"id":"26","name":"Hindi"},
   {"id":"27","name":"Kannada"},
   {"id":"28","name":"Konkani"},
   {"id":"29","name":"Malayalam"},
   {"id":"30","name":"Marathi"},
   {"id":"31","name":"Marwari"},
   {"id":"32","name":"Oriya"},
   {"id":"33","name":"Punjabi"},
   {"id":"34","name":"Sindhi"},
   {"id":"35","name":"Tamil"},
   {"id":"36","name":"Telugu"},
   {"id":"37","name":"Urdu"},
   {"id":"38","name":"Angika"},
   {"id":"39","name":"Arunachali"},
   {"id":"40","name":"Awadhi"},
   {"id":"41","name":"Bhojpuri"},
   {"id":"42","name":"Brij"},
   {"id":"43","name":"Bihari"},
   {"id":"44","name":"Badaga"},
   {"id":"45","name":"Chatisgarhi"},
   {"id":"46","name":"Dogri"},
   {"id":"47","name":"French"},
   {"id":"48","name":"Garhwali"},
   {"id":"49","name":"Garo"},
   {"id":"50","name":"Haryanvi"},
   {"id":"51","name":"Himachali/Pahari"},
   {"id":"52","name":"Kanauji"},
   {"id":"53","name":"Kashmiri"},
   {"id":"54","name":"Khandesi"},
   {"id":"55","name":"Khasi"},
   {"id":"56","name":"Koshali"},
   {"id":"57","name":"Kumaoni"},
   {"id":"58","name":"Kutchi"},
   {"id":"59","name":"Lepcha"},
   {"id":"60","name":"Ladacki"},
   {"id":"61","name":"Magahi"},
   {"id":"62","name":"Maithili"},
   {"id":"63","name":"Manipuri"},
   {"id":"64","name":"Miji"},
   {"id":"65","name":"Mizo"},
   {"id":"66","name":"Monpa"},
   {"id":"67","name":"Nicobarese"},
   {"id":"68","name":"Nepali"},
   {"id":"69","name":"Rajasthani"},
   {"id":"70","name":"Sanskrit"},
   {"id":"71","name":"Santhali"},
   {"id":"72","name":"Sourashtra"},
   {"id":"73","name":"Tripuri"},
   {"id":"74","name":"Tulu"}
],
"M_COUNTRYCODE":[
    {"id":"75","name":"- Select -"},				
    {"id":"76","name":"Antarctica (+672)"},				
    {"id":"77","name":"Argentina (+54)"},				
	{"id":"78","name":"Australia (+61)"},				
	{"id":"79","name":"Bangladesh (+880)"},				
	{"id":"80","name":"Belgium (+32)"},				
	{"id":"81","name":"Bhutan (+975)"},				
	{"id":"82","name":"Brazil (+55)"},				
	{"id":"83","name":"Canada (+1)"},				
	{"id":"84","name":"China (+86)"},				
	{"id":"85","name":"Egypt (+20)"},				
	{"id":"86","name":"France (+33)"},				
	{"id":"87","name":"Germany (+49)"},				
	{"id":"88","name":"Greenland (+299)"},				
	{"id":"89","name":"Hong Kong (+852)"},				
	{"id":"90","name":"India (+91)"},
	{"id":"91","name":"Indonesia (+62)"},
	{"id":"92","name":"Iran (+98)"},
	{"id":"93","name":"Iraq (+964)"},				
	{"id":"94","name":"Italy (+39)"},				
	{"id":"95","name":"Japan (+81)"},				
	{"id":"96","name":"Kuwait (+965)"},				
	{"id":"97","name":"Macau (+853)"},				
	{"id":"98","name":"Malaysia (+60)"},
	{"id":"99","name":"Maldives (+960)"},				
	{"id":"100","name":"Mexico (+52)"},				
	{"id":"101","name":"Myanmar (+95)"},				
	{"id":"102","name":"Nepal (+977)"},
	{"id":"103","name":"Netherlands (+31)"},				
	{"id":"104","name":"New Zealand (+64)"},				
	{"id":"105","name":"Northern Mariana Islands (+1)"},
	{"id":"106","name":"Norway (+47)"},
	{"id":"107","name":"Oman (+968)"},
	{"id":"108","name":"Pakistan (+92)"},				
	{"id":"109","name":"Philippines (+63)"},				
	{"id":"110","name":"Poland (+48)"},
	{"id":"111","name":"Portugal (+351)"},				
	{"id":"112","name":"Qatar (+9113)"},				
	{"id":"113","name":"Russia (+7)"},				
	{"id":"114","name":"Saudi Arabia (+966)"},				
	{"id":"115","name":"Singapore (+65)"},								
	{"id":"116","name":"Sweden (+46)"},
	{"id":"117","name":"Switzerland (+41)"},				
	{"id":"118","name":"United Arab Emirates (+971)"},
	{"id":"119","name":"United Kingdom (+44)"},
	{"id":"120","name":"United States of America (+1)"}	
],
"mcaste":[
	{"id":"0","name":"- Select Caste-"},	
	{"id":"1","name":"Achirapakkam Chettiar"},	
	{"id":"2","name":"Adi Andhra"},	
	{"id":"3","name":"Agamudayar / Arcot / Thuluva Vellala"},	
	{"id":"4","name":"Agaram Vellan Chettiar"},	
	{"id":"5","name":"Agnikula Kshatriya"},	
	{"id":"6","name":"Ahirwar"},	
	{"id":"7","name":"Aramari / Gabit"},	
	{"id":"8","name":"Arekatica"},	
	{"id":"9","name":"Arya Vysya"},	
	{"id":"10","name":"Ayira Vysya"},	
	{"id":"11","name":"Ayyaraka"},	
	{"id":"12","name":"Bairwa"},	
	{"id":"13","name":"Balai"},	
	{"id":"14","name":"Balija"},	
	{"id":"15","name":"Balija Naidu"},	
	{"id":"16","name":"Balija Reddy"},	
	{"id":"17","name":"Beri Chettiar"},	
	{"id":"18","name":"Besta"},	
	{"id":"19","name":"Bhatraju"},	
	{"id":"20","name":"Brahmin - Anaviln Desai"},	
	{"id":"21","name":"Brahmin - Baidhiki/Vaidhiki"},	
	{"id":"22","name":"Brahmin - Bardai"},	
	{"id":"23","name":"Brahmin - Bhargav"},	
	{"id":"24","name":"Brahmin - Dravida"},	
	{"id":"25","name":"Brahmin - Khadayata"},	
	{"id":"26","name":"Brahmin - Khedaval"},	
	{"id":"27","name":"Brahmin - Koteshwara / Kota (Madhwa )"},	
	{"id":"28","name":"Brahmin - Madhwa"},	
	{"id":"29","name":"Brahmin - Mevada"},	
	{"id":"30","name":"Brahmin - Niyogi"},	
	{"id":"31","name":"Brahmin - Others"},	
	{"id":"32","name":"Brahmin - Rajgor"},	
	{"id":"33","name":"Brahmin - Rarhi/Radhi"},	
	{"id":"34","name":"Brahmin - Sarua"},	
	{"id":"35","name":"Brahmin - Shivalli (Madhva)"},	
	{"id":"36","name":"Brahmin - Shri Gaud"},	
	{"id":"37","name":"Brahmin - Shri Mali"},	
	{"id":"38","name":"Brahmin - Shukla Yajurvedi"},	
	{"id":"39","name":"Brahmin - Smartha"},	
	{"id":"40","name":"Brahmin - Sri Vaishnava"},	
	{"id":"41","name":"Brahmin - Tapodhan"},	
	{"id":"42","name":"Brahmin - Vaidiki"},	
	{"id":"43","name":"Brahmin - Vaikhanasa"},	
	{"id":"44","name":"Brahmin - Valam"},	
	{"id":"45","name":"Brahmin - Velanadu"},	
	{"id":"46","name":"Brahmin - Zalora"},	
	{"id":"47","name":"Chattada Sri Vaishnava"},	
    {"id":"48","name":"Chettiar"},	
	{"id":"49","name":"Chippolu (Mera)"},	
	{"id":"50","name":"Darji"},	
	{"id":"51","name":"Deshmukh"},	
	{"id":"52","name":"Devanga"},	
	{"id":"53","name":"Devanga Chettiar"},	
	{"id":"54","name":"Dhanak"},	
	{"id":"55","name":"Dommala"},	
	{"id":"56","name":"Dravida  Brahmin"},	
	{"id":"57","name":"Ediga /Goud (Balija)"},	
	{"id":"58","name":"Elur Chetty"},	
	{"id":"59","name":"Gajula / Kavarai"},	
	{"id":"60","name":"Gandla"},	
	{"id":"61","name":"Gandla / Ganiga"},	
	{"id":"62","name":"Gavara"},	
	{"id":"63","name":"Goud"},	
	{"id":"64","name":"Gowda"},	
	{"id":"65","name":"Gowda - Kuruba Gowda"},	
	{"id":"66","name":"Intercaste"},	
	{"id":"67","name":"Isai Vellalar"},	
	{"id":"68","name":"Jaalari"},	
	{"id":"69","name":"Jandra"},	
	{"id":"70","name":"Jangam"},	
	{"id":"71","name":"Jetty/Malla"},	
	{"id":"72","name":"Jhadav"},	
	{"id":"73","name":"Julaha"},	
	{"id":"74","name":"Kachara"},	
	{"id":"75","name":"Kaikaala"},	
	{"id":"76","name":"Kalinga"},	
	{"id":"77","name":"Kalinga Vysya"},	
	{"id":"78","name":"Kamma"},	
	{"id":"79","name":"Kamma Naidu"},	
	{"id":"80","name":"Kanakkan Padanna"},	
	{"id":"81","name":"Kandara"},	
	{"id":"82","name":"Kapu"},	
	{"id":"83","name":"Kapu Naidu"},	
	{"id":"84","name":"Kapu Reddy"},	
	{"id":"85","name":"Karakala Bhakthula"},	
	{"id":"86","name":"Karni Bhakthula"},	
	{"id":"87","name":"Kasukara"},	
	{"id":"88","name":"Kavara"},	
	{"id":"89","name":"Kerala Mudali"},	
	{"id":"90","name":"Khatik"},	
	{"id":"91","name":"Kongu Chettiar"},	
    {"id":"92","name":"Kongu Nadar"},	
	{"id":"93","name":"Kori/Koli"},	
	{"id":"94","name":"Kshatriya"},	
	{"id":"95","name":"Kshatriya Raju"},	
	{"id":"96","name":"Kumaoni Rajput"},	
	{"id":"97","name":"Kummari"},	
	{"id":"98","name":"Kunbi Lonari"},	
	{"id":"99","name":"Kunbi Maratha"},	
	{"id":"100","name":"Kunbi Tirale"},	
	{"id":"101","name":"Kurni"},	
	{"id":"102","name":"Kuruba"},	
	{"id":"103","name":"Kuruhini Chetty"},	
	{"id":"104","name":"Kuruva"},	
	{"id":"105","name":"Linga Balija"},	
	{"id":"106","name":"Lingayath"},	
    {"id":"107","name":"Madhwa  Brahmin"},	
	{"id":"108","name":"Madiga"},	
	{"id":"109","name":"Mahendra"},	
	{"id":"110","name":"Mair Rajput Swarnkar"},	
	{"id":"111","name":"Mala"},	
	{"id":"112","name":"Malwani"},	
	{"id":"113","name":"Manjapudur Chettiar"},	
	{"id":"114","name":"Mannan / Velan / Vannan"},	
	{"id":"115","name":"Maratha"},	
	{"id":"116","name":"Maratha Kshatriya"},	
	{"id":"117","name":"Meghwal"},	
	{"id":"118","name":"Mera"},	
	{"id":"119","name":"Meru Darji"},	
	{"id":"120","name":"Modikarlu"},	
	{"id":"121","name":"Mudaliyar"},	
	{"id":"122","name":"Mudiraj"},	
	{"id":"123","name":"Munnuru Kapu"},	
	{"id":"124","name":"Musukama"},	
	{"id":"125","name":"Naagavamsam"},	
	{"id":"126","name":"Nadar"},	
	{"id":"127","name":"Nagaralu"},	
	{"id":"128","name":"Nai"},	
	{"id":"129","name":"Naidu"},	
	{"id":"130","name":"Naika"},	
	{"id":"131","name":"Namdarlu"},	
	{"id":"132","name":"Nattukottai Chettiar"},	
	{"id":"133","name":"Neeli"},	
	{"id":"134","name":"Neeli Saali"},	
	{"id":"135","name":"Nessi"},	
	{"id":"136","name":"Niyogi  Brahmin"},	
	{"id":"137","name":"Ontari"},	
	{"id":"138","name":"Padmasali"},	
	{"id":"139","name":"Padmashali"},	
	{"id":"140","name":"Pagadala"},	
	{"id":"141","name":"Pallan / Devandra Kula Vellalan"},	
	{"id":"142","name":"Panan"},	
	{"id":"143","name":"Pannirandam Chettiar"},	
	{"id":"144","name":"Paravan / Bharatar"},	
	{"id":"145","name":"Parit"},	
	{"id":"146","name":"Partraj"},	
	{"id":"147","name":"Parvatha Rajakulam"},	
	{"id":"148","name":"Paswan / Dusadh"},	
	{"id":"149","name":"Patil"},	
	{"id":"150","name":"Patnaick/Sistakaranam"},	
	{"id":"151","name":"Pattinavar"},	
	{"id":"152","name":"Pattusali"},	
	{"id":"153","name":"Perika"},	
	{"id":"154","name":"Poosala"},	
	{"id":"155","name":"Poundra"},	
    {"id":"156","name":"Pulaya /  Cheruman"},	
    {"id":"157","name":"Rajaka"},	
	{"id":"158","name":"Rajput"},	
	{"id":"159","name":"Reddy"},	
	{"id":"160","name":"Relli"},	
	{"id":"161","name":"Rohit / Chamar"},	
	{"id":"162","name":"SC"},	
	{"id":"163","name":"ST"},	
	{"id":"164","name":"Sadhu Chetty"},	
	{"id":"165","name":"Sagara (Uppara)"},	
	{"id":"166","name":"Saiva Pillai Tirunelveli"},	
	{"id":"167","name":"Samagar"},	
	{"id":"168","name":"Sambava"},	
	{"id":"169","name":"Satnami"},	
	{"id":"170","name":"Savji"},	
	{"id":"171","name":"Sengunthar/Kaikolar"},	
	{"id":"172","name":"Settibalija"},	
	{"id":"173","name":"Setty Balija"},	
	{"id":"174","name":"Shettigar"},	
	{"id":"175","name":"Shilpkar"},	
	{"id":"176","name":"Smartha  Brahmin"},	
	{"id":"177","name":"Sonkar"},	
	{"id":"178","name":"Sozhia Chetty"},	
	{"id":"179","name":"Sri  Vaishnava"},	
	{"id":"180","name":"Srisayana"},	
	{"id":"181","name":"Sugali (Naika)"},	
	{"id":"182","name":"Surya Balija"},	
	{"id":"183","name":"Telaga"},	
	{"id":"184","name":"Telugupatti"},	
	{"id":"185","name":"Thandan"},	
	{"id":"186","name":"Thogata Veerakshathriya"},	
	{"id":"187","name":"Thondai Mandala Vellalar"},	
	{"id":"188","name":"Thota"},	
	{"id":"189","name":"Togata"},	
	{"id":"190","name":"Turupu Kapu"},	
	{"id":"191","name":"Vada Balija"},	
	{"id":"192","name":"Vadambar"},	
	{"id":"193","name":"Vaddera"},	
	{"id":"194","name":"Vadugan"},	
	{"id":"195","name":"Vaidiki  Brahmin"},	
	{"id":"196","name":"Vaikhanasa  Brahmin"},	
	{"id":"197","name":"Vaishnava"},	
	{"id":"198","name":"Valmiki"},	
	{"id":"199","name":"Vani"},	
	{"id":"200","name":"Vaniya Chettiar"},	
	{"id":"201","name":"Vanjara"},	
	{"id":"202","name":"Veerakodi Vellala"},	
	{"id":"203","name":"Velama"},	
	{"id":"204","name":"Velanadu  Brahmin"},	
	{"id":"205","name":"Vellan Chettiars"},	
	{"id":"206","name":"Viswabrahmin"},	
	{"id":"207","name":"Vokkaliga"},	
	{"id":"208","name":"Yadav"},	
	{"id":"209","name":"Yadava Naidu"},	
	{"id":"210","name":"Yellapu"},	
	{"id":"211","name":"Other caste"}	
],
"hed":[
    {"id":"212","name":" Select Highest Education Details"},								
    {"id":"213","name":"-- Any Bachelors in Engineering / Computers --"},	
    {"id":"214","name":"Aeronautical Engineering"},
    {"id":"215","name":"B.Arch"},
    {"id":"216","name":"BCA"},
    {"id":"217","name":"BE"},
    {"id":"218","name":"B.Plan"},
    {"id":"219","name":"B.Sc IT/ Computer Science"},
    {"id":"220","name":"B.Tech."},
    {"id":"221","name":"Other Bachelor Degree in Engineering / Computers"},
    {"id":"222","name":"M.Arch."},
    {"id":"223","name":"MCA"},
    {"id":"224","name":"ME"},
    {"id":"225","name":"M.Sc. IT / Computer Science"},
    {"id":"226","name":"M.S.(Engg.)"},
    {"id":"227","name":"M.Tech."},
    {"id":"228","name":"PGDCA"},
    {"id":"229","name":"Other Masters Degree in Engineering / Computers"},
    {"id":"230","name":"Aviation Degree"},
    {"id":"231","name":"B.A."},
    {"id":"232","name":"B.Com."},
    {"id":"233","name":"B.Ed."},
    {"id":"234","name":"BFA"},
    {"id":"235","name":"BFT"},
    {"id":"236","name":"BLIS"},
    {"id":"237","name":"B.M.M."},
    {"id":"238","name":"B.Sc."},
    {"id":"239","name":"B.S.W"},
    {"id":"240","name":"B.Phil."},
    {"id":"241","name":"Other Bachelor Degree in Arts / Science / Commerce"},
    {"id":"242","name":"M.A."},
    {"id":"243","name":"MCom"},
    {"id":"244","name":"M.Ed."},
    {"id":"245","name":"MFA"},
    {"id":"246","name":"MLIS"},
    {"id":"247","name":"M.Sc."},
    {"id":"248","name":"MSW"},
    {"id":"249","name":"M.Phil."},
    {"id":"250","name":"Other Master Degree in Arts / Science / Commerce"},
    {"id":"251","name":"BBA"},
    {"id":"252","name":"BFM (Financial Management)"},
    {"id":"253","name":"BHM (Hotel Management)"},
    {"id":"254","name":"Other Bachelor Degree in Management"},
    {"id":"255","name":"MBA"},
    {"id":"256","name":"MFM (Financial Management)"},
    {"id":"257","name":"MHM  (Hotel Management)"},
    {"id":"258","name":"MHRM (Human Resource Management)"},
    {"id":"259","name":"PGDM"},
    {"id":"260","name":"Other Master Degree in Management"},
    {"id":"261","name":"B.A.M.S."},
    {"id":"262","name":"BDS"},
    {"id":"263","name":"BHMS"},
    {"id":"264","name":"BSMS"},
    {"id":"265","name":"BPharm"},
    {"id":"266","name":"BPT"},
    {"id":"267","name":"BUMS"},
    {"id":"268","name":"BVSc"},
    {"id":"269","name":"MBBS"},
    {"id":"270","name":"B.Sc. Nursing"},
    {"id":"271","name":"Other Bachelor Degree in Medicine"},
    {"id":"272","name":"MDS"},
    {"id":"273","name":"MD / MS (Medical)"},
    {"id":"274","name":"M.Pharm"},
    {"id":"275","name":"MPT"},
    {"id":"276","name":"MVSc"},
    {"id":"277","name":"Other Master Degree in Medicine"},
    {"id":"278","name":"BGL"},
    {"id":"279","name":"B.L."},
    {"id":"280","name":"LL.B."},
    {"id":"281","name":"Other Bachelor Degree in Legal"},
    {"id":"282","name":"LL.M."},
    {"id":"283","name":"M.L."},
    {"id":"284","name":"Other Master Degree in  Legal"},
    {"id":"285","name":"CA"},
    {"id":"286","name":"CFA (Chartered Financial Analyst)"},
    {"id":"287","name":"CS"},
    {"id":"288","name":"ICWA"},
    {"id":"289","name":"Other Degree in Finance"},
    {"id":"290","name":"IAS"},
    {"id":"291","name":"IES"},
    {"id":"292","name":"IFS"},
    {"id":"293","name":"IRS"},
    {"id":"294","name":"IPS"},
    {"id":"295","name":"Other Degree in Service"},
    {"id":"296","name":"Ph.D."},
    {"id":"297","name":"Diploma"},
    {"id":"298","name":"Polytechnic"},
    {"id":"299","name":"Trade School"},
    {"id":"300","name":"Others in Diploma"},
    {"id":"301","name":"Higher Secondary School / High School"}
],
"occupation":[
	{"id":"302","name":"Select Your Occupation"},
	{"id":"303","name":"Supervisor"},
	{"id":"304","name":"Officer"},
	{"id":"305","name":"Administrative Professional"},
	{"id":"306","name":"Executive"},
	{"id":"307","name":"Clerk"},
	{"id":"308","name":"Human Resources Professional"},
	{"id":"309","name":"Agriculture &amp; Farming Professional"},
	{"id":"310","name":"Pilot"},
	{"id":"311","name":"Air Hostess"},
	{"id":"312","name":"Airline Professional"},
	{"id":"313","name":"Architect"},
	{"id":"314","name":"Interior Designer"},
	{"id":"315","name":"Chartered Accountant"},
	{"id":"316","name":"Company Secretary"},
	{"id":"317","name":"Accounts/Finance Professional"},
	{"id":"318","name":"Banking Service Professional"},
	{"id":"319","name":"Auditor"},
	{"id":"320","name":"Financial Accountant"},
	{"id":"321","name":"Financial Analyst / Planning"},
	{"id":"322","name":"Fashion Designer"},
	{"id":"323","name":"Beautician"},
	{"id":"324","name":"Civil Services (IAS/IPS/IRS/IES/IFS)"},
	{"id":"325","name":"Army"},
	{"id":"326","name":"Navy"},
	{"id":"327","name":"Airforce"},
	{"id":"328","name":"Professor / Lecturer"},
	{"id":"329","name":"Teaching / Academician"},
	{"id":"330","name":"Education Professional"},
	{"id":"331","name":"Hotel / Hospitality Professional"},
	{"id":"332","name":"Software Professional"},
	{"id":"333","name":"Hardware Professional"},
	{"id":"334","name":"Engineer - Non IT"},
	{"id":"335","name":"Designer"},
	{"id":"336","name":"Lawyer &amp; Legal Professional"},
	{"id":"337","name":"Law Enforcement Officer"},
	{"id":"338","name":"Doctor"},
	{"id":"339","name":"Health Care Professional"},
	{"id":"340","name":"Paramedical Professional"},
	{"id":"341","name":"Nurse"},
	{"id":"342","name":"Marketing Professional"},
	{"id":"343","name":"Sales Professional"},
	{"id":"344","name":"Journalist"},
	{"id":"345","name":"Media Professional"},
	{"id":"346","name":"Entertainment Professional"},
	{"id":"347","name":"Event Management Professional"},
	{"id":"348","name":"Advertising / PR Professional"},
	{"id":"349","name":"Designer"},
	{"id":"350","name":"Mariner / Merchant Navy"},
	{"id":"360","name":"Scientist / Researcher"},
	{"id":"361","name":"CXO / President, Director, Chairman"},
	{"id":"362","name":"Business Analyst"},
	{"id":"363","name":"Consultant"},
	{"id":"364","name":"Customer Care Professional"},
	{"id":"365","name":"Social Worker"},
	{"id":"366","name":"Sportsman"},
	{"id":"367","name":"Technician"},
	{"id":"368","name":"Arts &amp; Craftsman"},
	{"id":"369","name":"Librarian"},
	{"id":"370","name":"Business Owner / Entrepreneur"},
	{"id":"371","name":"Manager"},
	{"id":"372","name":"-- OTHERS --"}
],
"curr":[
    {"id":"373","name":"-- Select Currency --"},
    {"id":"374","name":"Afghanistan - AFA"},
	{"id":"375","name":"Albania - ALL"},
	{"id":"376","name":"Algeria - DZD"},
	{"id":"377","name":"American Samoa - USD"},
	{"id":"378","name":"Andorra - EUR"},
	{"id":"379","name":"Angola - AON"},
	{"id":"380","name":"Anguilla - XCD"},
	{"id":"381","name":"Antarctica - XCD"},
	{"id":"382","name":"Antigua and Barbuda - XCD"},
	{"id":"383","name":"Argentina - ARS"},
	{"id":"384","name":"Armenia - AMD"},
	{"id":"385","name":"Aruba - AWG"},
	{"id":"386","name":"Australia - AUD"},
	{"id":"387","name":"Austria - EUR"},
	{"id":"388","name":"Azerbaijan - AZM"},
	{"id":"389","name":"Bahamas - BSD"},
	{"id":"390","name":"Bahrain - BHD"},
	{"id":"391","name":"Bangladesh - BDT"},
	{"id":"392","name":"Barbados - BBD"},
	{"id":"393","name":"Belarus - BYB"},
	{"id":"394","name":"Belgium - EUR"},
	{"id":"395","name":"Belize - BZD"},
	{"id":"396","name":"Benin - XOF"},
	{"id":"397","name":"Bermuda - BMD"},
	{"id":"398","name":"Bhutan - BTN"},
	{"id":"399","name":"Bolivia - BOB"},
	{"id":"400","name":"Bosnia and Herzegovina - BAM"},
	{"id":"401","name":"Botswana - BWP"},
	{"id":"402","name":"Bouvet Island - NOK"},
	{"id":"403","name":"Brazil - BRL"},
	{"id":"404","name":"British Indian Ocean Territory - USD"},
	{"id":"405","name":"British Virgin Islands - USD"},
	{"id":"406","name":"Brunei - BND"},
	{"id":"407","name":"Bulgaria - BGL"},
	{"id":"408","name":"Burkina Faso - XOF"},
	{"id":"409","name":"Burundi - BIF"},
	{"id":"410","name":"Cambodia - KHR"},
	{"id":"411","name":"Cameroon - XAF"},
	{"id":"412","name":"Canada - CAD"},
	{"id":"413","name":"Cape Verde - CVE"},
	{"id":"414","name":"Cayman Islands - KYD"},
	{"id":"415","name":"Central African Republic - XAF"},
	{"id":"416","name":"Chad - XAF"},
	{"id":"417","name":"Chile - CLP"},
	{"id":"418","name":"China - CNY"},
	{"id":"419","name":"Christmas Island - AUD"},
	{"id":"420","name":"Cocos Islands - AUD"},
	{"id":"421","name":"Colombia - COP"},
	{"id":"422","name":"Comoros - KMF"},
	{"id":"423","name":"Congo - XAF"},
	{"id":"424","name":"Cook Islands - NZD"},
	{"id":"425","name":"Costa Rica - CRC"},
	{"id":"426","name":"Croatia - HRK"},
	{"id":"427","name":"Cuba - CUP"},
	{"id":"428","name":"Cyprus - CYP"},
	{"id":"429","name":"Czech Republic - CZK"},
	{"id":"430","name":"Denmark - DKK"},
	{"id":"431","name":"Djibouti - DJF"},
	{"id":"432","name":"Dominica - XCD"},
	{"id":"433","name":"Dominican Republic - DOP"},
	{"id":"434","name":"East Timor - TPE"},
	{"id":"435","name":"Ecuador - ECS"},
	{"id":"436","name":"Egypt - EGP"},
	{"id":"437","name":"El Salvador - SVC"},
	{"id":"438","name":"Equatorial Guinea - XAF"},
	{"id":"439","name":"Eritrea - ERN"},
	{"id":"440","name":"Estonia - EEK"},
	{"id":"441","name":"Ethiopia - ETB"},
	{"id":"442","name":"Falkland Islands - FKP"},
	{"id":"443","name":"Faroe Islands - DKK"},
	{"id":"444","name":"Fiji - FJD"},
	{"id":"445","name":"Finland - EUR"},
	{"id":"446","name":"France - EUR"},
	{"id":"447","name":"French Guiana - EUR"},
	{"id":"448","name":"French Polynesia - XPF"},
	{"id":"449","name":"French Southern Territories - EUR"},
	{"id":"450","name":"Gabon - XAF"},
	{"id":"451","name":"Gambia - GMD"},
	{"id":"452","name":"Georgia - GEL"},
	{"id":"453","name":"Germany - EUR"},
	{"id":"454","name":"Ghana - GHC"},
	{"id":"455","name":"Gibraltar - GIP"},
	{"id":"456","name":"Greece - EUR"},
	{"id":"457","name":"Greenland - DKK"},
	{"id":"458","name":"Grenada - XCD"},
	{"id":"459","name":"Guadeloupe - EUR"},
	{"id":"460","name":"Guam - USD"},
	{"id":"461","name":"Guatemala - QTQ"},
	{"id":"462","name":"Guinea - GNF"},
	{"id":"463","name":"Guinea-Bissau - GWP"},
	{"id":"464","name":"Guyana - GYD"},
	{"id":"465","name":"Haiti - HTG"},
	{"id":"466","name":"Heard and McDonald Islands - AUD"},
	{"id":"467","name":"Honduras - HNL"},
	{"id":"468","name":"Hong Kong - HKD"},
	{"id":"469","name":"Hungary - HUF"},
	{"id":"470","name":"Iceland - ISK"},
	{"id":"471","name":"India - Rs."},
	{"id":"472","name":"Indonesia - IDR"},
	{"id":"473","name":"Iran - IRR"},
	{"id":"474","name":"Iraq - IQD"},
	{"id":"475","name":"Ireland - EUR"},
	{"id":"476","name":"Israel - ILS"},
	{"id":"477","name":"Italy - EUR"},
	{"id":"478","name":"Ivory Coast - XOF"},
	{"id":"479","name":"Jamaica - JMD"},
	{"id":"480","name":"Japan - JPY"},
	{"id":"481","name":"Jordan - JOD"},
	{"id":"482","name":"Kazakhstan - KZT"},
	{"id":"483","name":"Kenya - KES"},
	{"id":"484","name":"Kiribati - AUD"},
	{"id":"485","name":"Korea, North - KPW"},
	{"id":"486","name":"Korea, South - KRW"},
	{"id":"487","name":"Kuwait - KWD"},
	{"id":"488","name":"Kyrgyzstan - KGS"},
	{"id":"489","name":"Laos - LAK"},
	{"id":"490","name":"Latvia - LVL"},
	{"id":"491","name":"Lebanon - LBP"},
	{"id":"492","name":"Lesotho - LSL"},
	{"id":"493","name":"Liberia - LRD"},
	{"id":"494","name":"Libya - LYD"},
	{"id":"495","name":"Liechtenstein - CHF"},
	{"id":"496","name":"Lithuania - LTL"},
	{"id":"497","name":"Luxembourg - EUR"},
	{"id":"498","name":"Macau - MOP"},
	{"id":"499","name":"Macedonia - MKD"},
	{"id":"500","name":"Madagascar - MGF"},
	{"id":"501","name":"Malawi - MWK"},
	{"id":"502","name":"Malaysia - MYR"},
	{"id":"503","name":"Maldives - MVR"},
	{"id":"504","name":"Mali - XOF"},
	{"id":"505","name":"Malta - MTL"},
	{"id":"506","name":"Marshall Islands - USD"},
	{"id":"507","name":"Martinique - EUR"},
	{"id":"508","name":"Mauritania - MRO"},
	{"id":"509","name":"Mauritius - MUR"},
	{"id":"510","name":"Mayotte - EUR"},
	{"id":"511","name":"Mexico - MXN"},
	{"id":"512","name":"Micronesia, Federated States of - USD"},
	{"id":"513","name":"Moldova - MDL"},
	{"id":"514","name":"Monaco - EUR"},
	{"id":"515","name":"Mongolia - MNT"},
	{"id":"516","name":"Montserrat - XCD"},
	{"id":"517","name":"Morocco - MAD"},
	{"id":"518","name":"Mozambique - MZM"},
	{"id":"519","name":"Myanmar - MMK"},
	{"id":"520","name":"Namibia - NAD"},
	{"id":"521","name":"Nauru - AUD"},
	{"id":"522","name":"Nepal - NPR"},
	{"id":"523","name":"Netherlands - EUR"},
	{"id":"524","name":"Netherlands Antilles - ANG"},
	{"id":"525","name":"New Caledonia - XPF"},
	{"id":"526","name":"New Zealand - NZD"},
	{"id":"527","name":"Nicaragua - NIC"},
	{"id":"528","name":"Niger - XOF"},
	{"id":"529","name":"Nigeria - NGN"},
	{"id":"530","name":"Niue - NZD"},
	{"id":"531","name":"Norfolk Island - AUD"},
	{"id":"532","name":"Northern Mariana Islands - USD"},
	{"id":"533","name":"Norway - NOK"},
	{"id":"534","name":"Oman - OMR"},
	{"id":"535","name":"Pakistan - PKR"},
	{"id":"536","name":"Palau - USD"},
	{"id":"537","name":"Panama - PAB"},
	{"id":"538","name":"Papua New Guinea - PGK"},
	{"id":"539","name":"Paraguay - PYG"},
	{"id":"540","name":"Peru - PEN"},
	{"id":"541","name":"Philippines - PHP"},
	{"id":"542","name":"Pitcairn Island - NZD"},
	{"id":"543","name":"Poland - PLZ"},
	{"id":"544","name":"Portugal - EUR"},
	{"id":"545","name":"Puerto Rico - USD"},
	{"id":"546","name":"Qatar - QAR"},
	{"id":"547","name":"Reunion - EUR"},
	{"id":"548","name":"Romania - ROL"},
	{"id":"549","name":"Russia - RUR"},
	{"id":"550","name":"Rwanda - RWF"},
	{"id":"551","name":"S. Georgia and S. Sandwich Isls. - GBP"},
	{"id":"552","name":"Saint Kitts &amp; Nevis - XCD"},
	{"id":"553","name":"Saint Lucia - XCD"},
	{"id":"554","name":"Saint Vincent and The Grenadines - XCD"},
	{"id":"555","name":"Samoa - WST"},
	{"id":"556","name":"San Marino - ITL"},
	{"id":"557","name":"Sao Tome and Principe - STD"},
	{"id":"558","name":"Saudi Arabia - SAR"},
	{"id":"559","name":"Senegal - XOF"},
	{"id":"560","name":"Seychelles - SCR"},
	{"id":"561","name":"Sierra Leone - SLL"},
	{"id":"562","name":"Singapore - SGD"},
	{"id":"563","name":"Slovakia - SKK"},
	{"id":"564","name":"Slovenia - SIT"},
	{"id":"565","name":"Somalia - SOD"},
	{"id":"566","name":"South Africa - ZAR"},
	{"id":"567","name":"Spain - EUR"},
	{"id":"568","name":"Sri Lanka - LKR"},
	{"id":"569","name":"St. Helena - SHP"},
	{"id":"570","name":"St. Pierre and Miquelon - EUR"},
	{"id":"571","name":"Sudan - SDD"},
	{"id":"572","name":"Suriname - SRG"},
	{"id":"573","name":"Svalbard and Jan Mayen Islands - NOK"},
	{"id":"574","name":"Swaziland - SZL"},
	{"id":"575","name":"Sweden - SEK"},
	{"id":"576","name":"Switzerland - CHF"},
	{"id":"577","name":"Syria - SYP"},
	{"id":"578","name":"Taiwan - TWD"},
	{"id":"579","name":"Tajikistan - TJR"},
	{"id":"580","name":"Tanzania - TZS"},
	{"id":"581","name":"Thailand - THB"},
	{"id":"582","name":"Togo - XOF"},
	{"id":"583","name":"Tokelau - NZD"},
	{"id":"584","name":"Tonga - TOP"},
	{"id":"585","name":"Trinidad and Tobago - TTD"},
	{"id":"586","name":"Tunisia - TND"},
	{"id":"587","name":"Turkey - TRL"},
	{"id":"588","name":"Turkmenistan - TMM"},
	{"id":"589","name":"Turks and Caicos Islands - USD"},
	{"id":"590","name":"Tuvalu - AUD"},
	{"id":"591","name":"Uganda - UGS"},
	{"id":"592","name":"Ukraine - UAG"},
	{"id":"593","name":"United Arab Emirates - AED"},
	{"id":"594","name":"United Kingdom - GBP"},
	{"id":"595","name":"United States of America - USD"},
	{"id":"596","name":"Uruguay - UYP"},
	{"id":"597","name":"Uzbekistan - UZS"},
	{"id":"598","name":"Vanuatu - VUV"},
	{"id":"599","name":"Vatican City - EUR"},
	{"id":"600","name":"Venezuela - VUB"},
	{"id":"601","name":"Vietnam - VND"},
	{"id":"602","name":"Virgin Islands - USD"},
	{"id":"603","name":"Wallis and Futuna Islands - XPF"},
	{"id":"604","name":"Western Sahara - MAD"},
	{"id":"605","name":"Yemen - YER"},
	{"id":"606","name":"Yugoslavia (Former) - YUN"},
	{"id":"607","name":"Zaire - CDF"},
	{"id":"608","name":"Zambia - ZMK"},
	{"id":"609","name":"Zimbabwe - ZWD"},
	{"id":"610","name":"DR Congo - XAF"}
],
"myweight":[
    {"id":"611","name":"Select Your Weight"},
	{"id":"612","name":"below 45 kg"},
	{"id":"613","name":"46 kg"},
	{"id":"614","name":"47 kg"},
	{"id":"615","name":"48 kg"},
	{"id":"616","name":"49 kg"},
	{"id":"617","name":"50 kg"},
	{"id":"618","name":"51 kg"},
	{"id":"619","name":"52 kg"},
	{"id":"620","name":"53 kg"},
	{"id":"621","name":"54 kg"},
	{"id":"622","name":"55 kg"},
	{"id":"623","name":"56 kg"},
	{"id":"624","name":"57 kg"},
	{"id":"625","name":"58 kg"},
	{"id":"626","name":"59 kg"},
	{"id":"627","name":"60 kg"},
	{"id":"628","name":"61 kg"},
	{"id":"629","name":"62 kg"},
	{"id":"630","name":"63 kg"},
	{"id":"631","name":"64 kg"},
	{"id":"632","name":"65 kg"},
	{"id":"633","name":"66 kg"},
	{"id":"634","name":"67 kg"},
	{"id":"635","name":"68 kg"},
	{"id":"636","name":"69 kg"},
	{"id":"637","name":"70 kg"},
	{"id":"638","name":"71 kg"},
	{"id":"639","name":"72 kg"},
	{"id":"640","name":"73 kg"},
	{"id":"641","name":"74 kg"},
	{"id":"642","name":"75 kg"},
	{"id":"643","name":"76 kg"},
	{"id":"644","name":"77 kg"},
	{"id":"645","name":"78 kg"},
	{"id":"679","name":"80 kg"},
	{"id":"647","name":"81 kg"},
	{"id":"648","name":"82 kg"},
	{"id":"649","name":"83 kg"},
	{"id":"650","name":"84 kg"},
	{"id":"651","name":"85 kg"},
	{"id":"652","name":"86 kg"},
	{"id":"653","name":"87 kg"},
	{"id":"654","name":"88 kg"},
	{"id":"655","name":"89 kg"},
	{"id":"656","name":"90 kg"},
	{"id":"657","name":"91 kg"},
	{"id":"658","name":"92 kg"},
	{"id":"659","name":"93 kg"},
	{"id":"660","name":"94 kg"},
	{"id":"661","name":"95 kg"},
	{"id":"662","name":"96 kg"},
	{"id":"663","name":"97 kg"},
	{"id":"664","name":"98 kg"},
	{"id":"665","name":"99 kg"},
	{"id":"666","name":"100 kg"},
	{"id":"667","name":"101 kg"},
	{"id":"668","name":"102 kg"},
	{"id":"669","name":"103 kg"},
	{"id":"670","name":"104 kg"},
	{"id":"671","name":"105 kg"},
	{"id":"672","name":"106 kg"},
	{"id":"673","name":"107 kg"},
	{"id":"674","name":"108 kg"},
	{"id":"675","name":"109 kg"},
	{"id":"676","name":"110 kg"},
	{"id":"677","name":"111 kg"},
	{"id":"678","name":"112 kg"},
	{"id":"679","name":"113 kg"},
	{"id":"680","name":"114 kg"},
	{"id":"681","name":"115 kg"},
	{"id":"682","name":"116 kg"},
	{"id":"683","name":"117 kg"},
	{"id":"684","name":"118 kg"},
	{"id":"685","name":"119 kg"},
	{"id":"686","name":"120 kg"},
	{"id":"687","name":"Above 120 kg"}
],
"mystar":[
    {"id":"688","name":"Select Your Star"},
	{"id":"689","name":"Aswini"},
	{"id":"690","name":"Bharani"},
	{"id":"691","name":"Kruthiga"},
	{"id":"692","name":"Rohini"},
	{"id":"693","name":"Mrigasira"},
	{"id":"694","name":"Arudra"},
	{"id":"695","name":"Punarvasu"},
	{"id":"696","name":"Pushya"},
	{"id":"697","name":"Asilesha"},
	{"id":"698","name":"Makha"},
	{"id":"699","name":"Poorvaphalguni"},
	{"id":"700","name":"Uthiraphalguni"},
	{"id":"701","name":"Hastha"},
	{"id":"702","name":"Chitha"},
	{"id":"703","name":"Swathi"},
	{"id":"704","name":"Visaka"},
	{"id":"705","name":"Anuradha"},
	{"id":"706","name":"Jyeshta"},
	{"id":"707","name":"Moola"},
	{"id":"708","name":"Poorvashada"},
	{"id":"709","name":"Uthrashada"},
	{"id":"710","name":"Sravana"},
	{"id":"711","name":"Dhanishta"},
	{"id":"712","name":"Stabhishek"},
	{"id":"713","name":"Poorvabhadra"},
	{"id":"714","name":"Uthirabhadra"},
	{"id":"715","name":"Revathi"}
],
"myraasi":[
     {"id":"716","name":"Select Your Raasi"},
	 {"id":"717","name":"Mesha"},
	 {"id":"718","name":"Vrishaba"},
	 {"id":"719","name":"Mithuna"},
	 {"id":"720","name":"Karkata"},
	 {"id":"721","name":"Simha"},
	 {"id":"722","name":"Kanya"},
	 {"id":"723","name":"Tula"},
	 {"id":"724","name":"Vrischika"},
	 {"id":"725","name":"Dhanus"},
	 {"id":"726","name":"Makara"},
	 {"id":"727","name":"Kumbha"},
	 {"id":"728","name":"Meena"}
],
"tbhour":[
    {"id":"729","name":"Hours"},
	{"id":"730","name":"1"},
	{"id":"731","name":"2"},
	{"id":"732","name":"3"},
	{"id":"733","name":"4"},
	{"id":"734","name":"5"},
	{"id":"735","name":"6"},
	{"id":"736","name":"7"},
	{"id":"737","name":"8"},
	{"id":"738","name":"9"},
	{"id":"739","name":"10"},
	{"id":"740","name":"11"},
	{"id":"741","name":"12"}
],
"tbminute":[
    {"id":"742","name":"Mins"},
	{"id":"743","name":"00"},
	{"id":"744","name":"01"},
	{"id":"745","name":"02"},
	{"id":"746","name":"03"},
	{"id":"747","name":"04"},
	{"id":"748","name":"05"},
	{"id":"749","name":"06"},
	{"id":"750","name":"07"},
	{"id":"751","name":"08"},
	{"id":"752","name":"09"},
	{"id":"753","name":"10"},
	{"id":"754","name":"11"},
	{"id":"755","name":"12"},
	{"id":"756","name":"13"},
	{"id":"757","name":"14"},
	{"id":"758","name":"15"},
	{"id":"759","name":"16"},
	{"id":"760","name":"17"},
	{"id":"761","name":"18"},
	{"id":"762","name":"19"},
	{"id":"763","name":"20"},
	{"id":"764","name":"21"},
	{"id":"765","name":"22"},
	{"id":"766","name":"23"},
	{"id":"767","name":"24"},
	{"id":"768","name":"25"},
	{"id":"769","name":"26"},
	{"id":"770","name":"27"},
	{"id":"771","name":"28"},
	{"id":"772","name":"29"},
	{"id":"773","name":"30"},
	{"id":"774","name":"31"},
	{"id":"775","name":"32"},
	{"id":"776","name":"33"},
	{"id":"777","name":"34"},
	{"id":"778","name":"35"},
	{"id":"779","name":"36"},
	{"id":"780","name":"37"},
	{"id":"781","name":"38"},
	{"id":"782","name":"39"},
	{"id":"783","name":"40"},
	{"id":"784","name":"41"},
	{"id":"785","name":"42"},
	{"id":"786","name":"43"},
	{"id":"787","name":"44"},
	{"id":"788","name":"45"},
	{"id":"789","name":"46"},
	{"id":"790","name":"47"},
	{"id":"791","name":"48"},
	{"id":"792","name":"49"},
	{"id":"793","name":"50"},
	{"id":"794","name":"51"},
	{"id":"795","name":"52"},
	{"id":"796","name":"53"},
	{"id":"797","name":"54"},
	{"id":"798","name":"55"},
	{"id":"799","name":"56"},
	{"id":"800","name":"57"},
	{"id":"801","name":"58"},
	{"id":"802","name":"59"}
],
"PM_COUNTRYCODE":[
    {"id":"803","name":"- Select -"},				
    {"id":"804","name":"Antarctica (+672)"},				
    {"id":"805","name":"Argentina (+54)"},				
	{"id":"806","name":"Australia (+61)"},				
	{"id":"807","name":"Bangladesh (+880)"},				
	{"id":"808","name":"Belgium (+32)"},				
	{"id":"809","name":"Bhutan (+975)"},				
	{"id":"810","name":"Brazil (+55)"},				
	{"id":"811","name":"Canada (+1)"},				
	{"id":"812","name":"China (+86)"},				
	{"id":"813","name":"Egypt (+20)"},				
	{"id":"814","name":"France (+33)"},				
	{"id":"815","name":"Germany (+49)"},				
	{"id":"816","name":"Greenland (+299)"},				
	{"id":"817","name":"Hong Kong (+852)"},				
	{"id":"818","name":"India (+91)"},
	{"id":"819","name":"Indonesia (+62)"},
	{"id":"820","name":"Iran (+98)"},
	{"id":"821","name":"Iraq (+964)"},				
	{"id":"822","name":"Italy (+39)"},				
	{"id":"823","name":"Japan (+81)"},				
	{"id":"824","name":"Kuwait (+965)"},				
	{"id":"825","name":"Macau (+853)"},				
	{"id":"826","name":"Malaysia (+60)"},
	{"id":"827","name":"Maldives (+960)"},				
	{"id":"828","name":"Mexico (+52)"},				
	{"id":"829","name":"Myanmar (+95)"},				
	{"id":"830","name":"Nepal (+977)"},
	{"id":"831","name":"Netherlands (+31)"},				
	{"id":"832","name":"New Zealand (+64)"},				
	{"id":"833","name":"Northern Mariana Islands (+1)"},
	{"id":"834","name":"Norway (+47)"},
	{"id":"835","name":"Oman (+968)"},
	{"id":"836","name":"Pakistan (+92)"},				
	{"id":"837","name":"Philippines (+63)"},				
	{"id":"838","name":"Poland (+48)"},
	{"id":"839","name":"Portugal (+351)"},				
	{"id":"840","name":"Qatar (+9113)"},				
	{"id":"841","name":"Russia (+7)"},				
	{"id":"842","name":"Saudi Arabia (+966)"},				
	{"id":"843","name":"Singapore (+65)"},								
	{"id":"844","name":"Sweden (+46)"},
	{"id":"845","name":"Switzerland (+41)"},				
	{"id":"846","name":"United Arab Emirates (+971)"},
	{"id":"847","name":"United Kingdom (+44)"},
	{"id":"848","name":"United States of America (+1)"}	
]}
